LICENSE
MANIFEST.in
README.md
setup.cfg
setup.py
glowaurora/__init__.py
glowaurora/plots.py
glowaurora/runglow_future.py
glowaurora/runmsisGLOW.py
glowaurora.egg-info/PKG-INFO
glowaurora.egg-info/SOURCES.txt
glowaurora.egg-info/dependency_links.txt
glowaurora.egg-info/entry_points.txt
glowaurora.egg-info/requires.txt
glowaurora.egg-info/top_level.txt
iri/ccir11.asc
iri/ccir12.asc
iri/ccir13.asc
iri/ccir14.asc
iri/ccir15.asc
iri/ccir16.asc
iri/ccir17.asc
iri/ccir18.asc
iri/ccir19.asc
iri/ccir20.asc
iri/ccir21.asc
iri/ccir22.asc
iri/ursi11.asc
iri/ursi12.asc
iri/ursi13.asc
iri/ursi14.asc
iri/ursi15.asc
iri/ursi16.asc
iri/ursi17.asc
iri/ursi18.asc
iri/ursi19.asc
iri/ursi20.asc
iri/ursi21.asc
iri/ursi22.asc
src/aurora_sub.f
src/cglow.h
src/dayglow_sub.f
src/egrid.f
src/ephoto.f
src/ephoto_xn2.dat
src/ephoto_xo.dat
src/ephoto_xo2.dat
src/etrans.f
src/exsect.f
src/fieldm.f
src/gchem.f
src/geomag.f
src/glow.f
src/iri90.f
src/maxt.f
src/nrlmsise00.f
src/qback.f
src/rcolum.f
src/rout.f
src/snoem.f
src/snoem_eof.dat
src/snoemint.f
src/solzen.f
src/ssflux.f
src/ssflux_euvac.dat
src/ssflux_hint.dat
src/vquart.f
tests/test_all.py
tests/test_fort.py
tests/test_snoem.py