Metadata-Version: 2.1
Name: glowaurora
Version: 1.2.2
Summary: GLobal airglOW Model of auroral and airglow emissions
Home-page: https://github.com/scivision/glowaurora
Author: Stan Solomon; Liam Kilcommons; Michael Hirsch, Ph.D.
Author-email: scivision@users.noreply.github.com
License: UNKNOWN
Keywords: aurora,airglow
Platform: UNKNOWN
Classifier: Development Status :: 4 - Beta
Classifier: Environment :: Console
Classifier: Intended Audience :: Science/Research
Classifier: Operating System :: OS Independent
Classifier: Programming Language :: Fortran
Classifier: Programming Language :: Python :: 3.6
Classifier: Programming Language :: Python :: 3.7
Classifier: Topic :: Scientific/Engineering :: Atmospheric Science
Requires-Python: >= 3.6
Provides-Extra: tests
Provides-Extra: io
Provides-Extra: plots
